mindquantum/__init__.py
mindquantum/__main__.py
mindquantum/_math.cpython-39-aarch64-linux-gnu.so
mindquantum/_mq_chem.cpython-39-aarch64-linux-gnu.so
mindquantum/_mq_matrix.cpython-39-aarch64-linux-gnu.so
mindquantum/_mq_stabilizer.cpython-39-aarch64-linux-gnu.so
mindquantum/_mq_vector.cpython-39-aarch64-linux-gnu.so
mindquantum/mqbackend.cpython-39-aarch64-linux-gnu.so
mindquantum/algorithm/__init__.py
mindquantum/algorithm/compiler/__init__.py
mindquantum/algorithm/compiler/dag/__init__.py
mindquantum/algorithm/compiler/dag/dag.py
mindquantum/algorithm/compiler/decompose/__init__.py
mindquantum/algorithm/compiler/decompose/utils.py
mindquantum/algorithm/compiler/decompose/fixed_decompose/__init__.py
mindquantum/algorithm/compiler/decompose/fixed_decompose/h_related.py
mindquantum/algorithm/compiler/decompose/fixed_decompose/rx_related.py
mindquantum/algorithm/compiler/decompose/fixed_decompose/rxx_related.py
mindquantum/algorithm/compiler/decompose/fixed_decompose/ry_related.py
mindquantum/algorithm/compiler/decompose/fixed_decompose/ryy_related.py
mindquantum/algorithm/compiler/decompose/fixed_decompose/rz_related.py
mindquantum/algorithm/compiler/decompose/fixed_decompose/rzz_related.py
mindquantum/algorithm/compiler/decompose/fixed_decompose/s_related.py
mindquantum/algorithm/compiler/decompose/fixed_decompose/swap_related.py
mindquantum/algorithm/compiler/decompose/fixed_decompose/t_related.py
mindquantum/algorithm/compiler/decompose/fixed_decompose/x_related.py
mindquantum/algorithm/compiler/decompose/fixed_decompose/y_related.py
mindquantum/algorithm/compiler/decompose/fixed_decompose/z_related.py
mindquantum/algorithm/compiler/decompose/universal_decompose/__init__.py
mindquantum/algorithm/compiler/decompose/universal_decompose/one_qubit_decompose.py
mindquantum/algorithm/compiler/decompose/universal_decompose/qs_and_cu_decompose.py
mindquantum/algorithm/compiler/decompose/universal_decompose/two_qubit_decompose.py
mindquantum-0.11.0.dist-info/METADATA
mindquantum-0.11.0.dist-info/WHEEL
mindquantum-0.11.0.dist-info/entry_points.txt
mindquantum-0.11.0.dist-info/top_level.txt
mindquantum-0.11.0.dist-info/RECORD
