Metadata-Version: 2.1
Name: mindquantum
Version: 0.11.0
Summary: A hybrid quantum-classic framework for quantum computing
Author-email: The MindSpore Authors <contact@mindspore.cn>
License: Apache License Version 2.0
Project-URL: Homepage, https://www.mindspore.cn/mindquantum/docs/en/master/index.html
Project-URL: Download (Gitee), https://gitee.com/mindspore/mindquantum/tags
Project-URL: Source (Gitee), https://gitee.com/mindspore/mindquantum
Project-URL: Issue Tracker, https://gitee.com/mindspore/mindquantum/issues
Project-URL: Download (GitHub), https://github.com/mindspore-ai/mindquantum/tags
Project-URL: Source (GitHub), https://github.com/mindspore-ai/mindquantum
Project-URL: Documentation, https://www.mindspore.cn/mindquantum/docs/en/master/index.html
Classifier: License :: OSI Approved :: Apache Software License
Classifier: Topic :: Software Development :: Libraries :: Python Modules
Classifier: Programming Language :: Python :: 3 :: Only
Classifier: Programming Language :: Python :: 3.7
Classifier: Programming Language :: Python :: 3.8
Classifier: Programming Language :: Python :: 3.9
Classifier: Programming Language :: Python :: 3.10
Classifier: Programming Language :: Python :: 3.11
Requires-Python: >=3.7
Requires-Dist: scipy>=1.5.3
Requires-Dist: matplotlib>=3.4.3
Requires-Dist: rich==10.9.0
Requires-Dist: importlib-metadata>=0.9; python_version < "3.8"
Requires-Dist: typing-extensions; python_version < "3.8"
Provides-Extra: docs
Requires-Dist: sphinx; extra == "docs"
Requires-Dist: sphinx-rtd-theme; extra == "docs"
Requires-Dist: breathe; extra == "docs"
Requires-Dist: myst-parser; extra == "docs"
Provides-Extra: mindspore
Requires-Dist: mindspore; extra == "mindspore"
Provides-Extra: test
Requires-Dist: pytest; extra == "test"
Requires-Dist: pytest-cov; extra == "test"
Requires-Dist: pytest-mock; extra == "test"
Requires-Dist: mock; extra == "test"
